mk1pass/CHECKSUM-SHA3-256.py
mk1pass/__init__.py
mk1pass/__main__.py
mk1pass/mk1pass.py
mk1pass/printdv.py
mk1pass-0.0.5.dist-info/LICENSE
mk1pass-0.0.5.dist-info/METADATA
mk1pass-0.0.5.dist-info/WHEEL
mk1pass-0.0.5.dist-info/entry_points.txt
mk1pass-0.0.5.dist-info/top_level.txt
mk1pass-0.0.5.dist-info/RECORD
